drilldown/__init__.py
drilldown/_version.py
drilldown/app.py
drilldown/callbacks.py
drilldown/config.py
drilldown/constants.py
drilldown/layout.py
drilldown/utils.py
drilldown/feature_store/__init__.py
drilldown/feature_store/column.py
drilldown/feature_store/constants.py
drilldown/feature_store/dataset.py
drilldown/feature_store/feature_store.py
drilldown/feature_store/uri_handler.py
drilldown/helpers/__init__.py
drilldown/helpers/create_demo_data.py
drilldown/internal_assets/custom_style.css
drilldown/internal_assets/logo.svg
drilldown/pages/__init__.py
drilldown/pages/analyze_page.py
drilldown/pages/explore_page.py
drilldown/pages/home_page.py
drilldown/pages/monitor_page.py
drilldown/pages/analyze/__init__.py
drilldown/pages/analyze/algorithms.py
drilldown/pages/explore/__init__.py
drilldown/pages/explore/chart.py
drilldown/pages/explore/grid.py
drilldown/pages/explore/sample_view.py
drilldown/pages/explore/update_chart.py
drilldown/pages/explore/update_grid.py
drilldown/pages/explore/update_sample_view.py
drilldown/pages/monitor/__init__.py
drilldown/pages/monitor/algorithms.py
drilldown-0.1.1.dist-info/METADATA
drilldown-0.1.1.dist-info/WHEEL
drilldown-0.1.1.dist-info/entry_points.txt
drilldown-0.1.1.dist-info/licenses/LICENSE
drilldown-0.1.1.dist-info/RECORD
